fsspec_git_annex-0.1.3.dist-info/METADATA
fsspec_git_annex-0.1.3.dist-info/WHEEL
fsspec_git_annex-0.1.3.dist-info/entry_points.txt
fsspec_git_annex-0.1.3.dist-info/licenses/LICENSES/Apache-2.0.txt
fsspec_git_annex-0.1.3.dist-info/licenses/LICENSES/CC0-1.0.txt
fsspec_git_annex/__init__.py
fsspec_git_annex/cli/__init__.py
fsspec_git_annex/cli/git_annex_mount.py
fsspec_git_annex/filesystem.py
fsspec_git_annex/git.py
fsspec_git_annex/git_annex.py
fsspec_git_annex-0.1.3.dist-info/RECORD
