Metadata-Version: 2.1
Name: fsspec-git-annex
Version: 0.1.3
Summary: A fsspec implementation for git-annex repositories
Keywords: datalad fsspec git-annex
Author-Email: Matthias Riße <m.risse@fz-juelich.de>
License: Apache License
Classifier: Programming Language :: Python :: 3
Classifier: License :: OSI Approved :: Apache Software License
Classifier: Operating System :: OS Independent
Project-URL: Homepage, https://github.com/matrss/fsspec-git-annex
Requires-Python: >=3.9
Requires-Dist: fsspec[fuse]>=2023.9.0
